cylestio_perimeter-2.4.1.dist-info/licenses/LICENSE
src/__init__.py
src/main.py
src/config/__init__.py
src/config/settings.py
src/events/__init__.py
src/events/anthropic.py
src/events/base.py
src/events/openai.py
src/events/types.py
src/interceptors/__init__.py
src/interceptors/event_recorder.py
src/interceptors/http_recorder.py
src/interceptors/message_logger.py
src/interceptors/printer.py
src/interceptors/test_recorder.py
src/interceptors/live_trace/ANALYSIS_FLOW.md
src/interceptors/live_trace/CLAUDE.md
src/interceptors/live_trace/README.md
src/interceptors/live_trace/__init__.py
src/interceptors/live_trace/interceptor.py
src/interceptors/live_trace/model_downloader.py
src/interceptors/live_trace/models.py
src/interceptors/live_trace/server.py
src/interceptors/live_trace/api/__init__.py
src/interceptors/live_trace/frontend/.gitignore
src/interceptors/live_trace/frontend/.prettierrc
src/interceptors/live_trace/frontend/README.md
src/interceptors/live_trace/frontend/eslint.config.js
src/interceptors/live_trace/frontend/index.html
src/interceptors/live_trace/frontend/package-lock.json
src/interceptors/live_trace/frontend/package.json
src/interceptors/live_trace/frontend/tsconfig.json
src/interceptors/live_trace/frontend/vite.config.ts
src/interceptors/live_trace/frontend/vitest.shims.d.ts
src/interceptors/live_trace/frontend/.storybook/main.ts
src/interceptors/live_trace/frontend/.storybook/manager.ts
src/interceptors/live_trace/frontend/.storybook/preview-head.html
src/interceptors/live_trace/frontend/.storybook/preview.ts
src/interceptors/live_trace/frontend/.storybook/vitest.setup.ts
src/interceptors/live_trace/frontend/docs/api-endpoint-patterns.md
src/interceptors/live_trace/frontend/docs/component-creation-guide.md
src/interceptors/live_trace/frontend/docs/components-index.md
src/interceptors/live_trace/frontend/docs/storybook-best-practices.md
src/interceptors/live_trace/frontend/docs/theme-design-tokens.md
src/interceptors/live_trace/frontend/docs/troubleshooting.md
cylestio_perimeter-2.4.1.dist-info/METADATA
cylestio_perimeter-2.4.1.dist-info/WHEEL
cylestio_perimeter-2.4.1.dist-info/entry_points.txt
cylestio_perimeter-2.4.1.dist-info/top_level.txt
cylestio_perimeter-2.4.1.dist-info/RECORD
