Metadata-Version: 2.4
Name: cylestio-perimeter
Version: 2.4.1
Summary: A configurable Python proxy server for LLM API requests with middleware support
Author-email: Cylestio <contact@cylestio.com>
License-Expression: Apache-2.0
Project-URL: Homepage, https://github.com/cylestio/cylestio-perimeter
Project-URL: Repository, https://github.com/cylestio/cylestio-perimeter
Project-URL: Issues, https://github.com/cylestio/cylestio-perimeter/issues
Classifier: Development Status :: 4 - Beta
Classifier: Intended Audience :: Developers
Classifier: Programming Language :: Python :: 3
Classifier: Programming Language :: Python :: 3.9
Classifier: Programming Language :: Python :: 3.10
Classifier: Programming Language :: Python :: 3.11
Classifier: Programming Language :: Python :: 3.12
Classifier: Topic :: Internet :: Proxy Servers
Classifier: Topic :: Software Development :: Libraries :: Python Modules
Requires-Python: >=3.9
License-File: LICENSE
Requires-Dist: fastapi>=0.109.0
Requires-Dist: httpx>=0.26.0
Requires-Dist: pydantic>=2.5.0
Requires-Dist: pydantic-settings>=2.1.0
Requires-Dist: pyyaml>=6.0.1
Requires-Dist: typer>=0.16.0
Requires-Dist: uvicorn>=0.27.0
Requires-Dist: python-multipart>=0.0.6
Requires-Dist: python-dotenv>=1.0.0
Requires-Dist: descope>=1.7.7
Requires-Dist: Jinja2>=3.1.0
Requires-Dist: numpy>=1.24.3
Requires-Dist: presidio-analyzer>=2.2.354
Requires-Dist: spacy>=3.7.0
Requires-Dist: sse-starlette>=1.8.2
Provides-Extra: dev
Requires-Dist: pytest>=7.4.4; extra == "dev"
Requires-Dist: pytest-asyncio>=0.23.3; extra == "dev"
Requires-Dist: pytest-mock>=3.12.0; extra == "dev"
Requires-Dist: pytest-cov>=4.1.0; extra == "dev"
Requires-Dist: black>=23.12.1; extra == "dev"
Requires-Dist: ruff>=0.1.11; extra == "dev"
Requires-Dist: mypy>=1.8.0; extra == "dev"
Requires-Dist: isort>=5.13.2; extra == "dev"
Requires-Dist: pre-commit>=3.6.0; extra == "dev"
Requires-Dist: ipython>=8.19.0; extra == "dev"
Requires-Dist: coverage>=7.4.0; extra == "dev"
Requires-Dist: types-PyYAML>=6.0.12.12; extra == "dev"
Dynamic: license-file
